odoo9_addon_website_breadcrumb-9.0.1.0.0.99.dev6-py3.8-nspkg.pth
odoo_addons/website_breadcrumb/README.rst
odoo_addons/website_breadcrumb/__init__.py
odoo_addons/website_breadcrumb/__openerp__.py
odoo_addons/website_breadcrumb/i18n/ar.po
odoo_addons/website_breadcrumb/i18n/ca.po
odoo_addons/website_breadcrumb/i18n/de.po
odoo_addons/website_breadcrumb/i18n/el.po
odoo_addons/website_breadcrumb/i18n/el_GR.po
odoo_addons/website_breadcrumb/i18n/en.po
odoo_addons/website_breadcrumb/i18n/es.po
odoo_addons/website_breadcrumb/i18n/es_CR.po
odoo_addons/website_breadcrumb/i18n/es_MX.po
odoo_addons/website_breadcrumb/i18n/es_VE.po
odoo_addons/website_breadcrumb/i18n/fi.po
odoo_addons/website_breadcrumb/i18n/fr.po
odoo_addons/website_breadcrumb/i18n/gl.po
odoo_addons/website_breadcrumb/i18n/hr.po
odoo_addons/website_breadcrumb/i18n/hu.po
odoo_addons/website_breadcrumb/i18n/it.po
odoo_addons/website_breadcrumb/i18n/ja.po
odoo_addons/website_breadcrumb/i18n/lt.po
odoo_addons/website_breadcrumb/i18n/lv.po
odoo_addons/website_breadcrumb/i18n/mk.po
odoo_addons/website_breadcrumb/i18n/mn.po
odoo_addons/website_breadcrumb/i18n/nl.po
odoo_addons/website_breadcrumb/i18n/pl.po
odoo_addons/website_breadcrumb/i18n/pt.po
odoo_addons/website_breadcrumb/i18n/pt_BR.po
odoo_addons/website_breadcrumb/i18n/ro.po
odoo_addons/website_breadcrumb/i18n/ru.po
odoo_addons/website_breadcrumb/i18n/sl.po
odoo_addons/website_breadcrumb/i18n/sv.po
odoo_addons/website_breadcrumb/i18n/website_breadcrumb.pot
odoo_addons/website_breadcrumb/i18n/zh_CN.po
odoo_addons/website_breadcrumb/models/__init__.py
odoo_addons/website_breadcrumb/models/website.py
odoo_addons/website_breadcrumb/static/description/icon.png
odoo_addons/website_breadcrumb/static/description/icon.svg
odoo_addons/website_breadcrumb/views/layout.xml
odoo_addons/website_breadcrumb/views/templates.xml
odoo9_addon_website_breadcrumb-9.0.1.0.0.99.dev6.dist-info/METADATA
odoo9_addon_website_breadcrumb-9.0.1.0.0.99.dev6.dist-info/WHEEL
odoo9_addon_website_breadcrumb-9.0.1.0.0.99.dev6.dist-info/namespace_packages.txt
odoo9_addon_website_breadcrumb-9.0.1.0.0.99.dev6.dist-info/top_level.txt
odoo9_addon_website_breadcrumb-9.0.1.0.0.99.dev6.dist-info/RECORD
