Metadata-Version: 2.1
Name: odoo9-addon-website-breadcrumb
Version: 9.0.1.0.0.99.dev6
Summary: Let you have breadcrumbs in website pages
Home-page: https://grupoesoc.es/
Author: Grupo ESOC Ingeniería de Servicios, Odoo Community Association (OCA)
Author-email: support@odoo-community.org
License: LGPL-3
Platform: UNKNOWN
Classifier: Programming Language :: Python
Classifier: Framework :: Odoo
Classifier: Framework :: Odoo :: 9.0
Classifier: License :: OSI Approved :: GNU Lesser General Public License v3 (LGPLv3)
Requires-Python: ~=2.7
Requires-Dist: odoo (<9.1a,>=9.0a)
